README.md
setup.py
bingau/__init__.py
bingau/binomial_distribution.py
bingau/gaussian_distribution.py
bingau/general_distribution.py
bingau.egg-info/PKG-INFO
bingau.egg-info/SOURCES.txt
bingau.egg-info/dependency_links.txt
bingau.egg-info/not-zip-safe
bingau.egg-info/requires.txt
bingau.egg-info/top_level.txt