Metadata-Version: 1.2
Name: bingau
Version: 1.0
Summary: Gaussian & Binomial distributions
Home-page: https://github.com/tyagihardik42/bingau
Author: Hardik Tyagi
Author-email: tyagi.hardik42@yahoo.com
License: UNKNOWN
Project-URL: Bug Reports, https://github.com/tyagihardik42/bingau/issues
Project-URL: Funding, https://donate.pypi.org
Project-URL: Say Thanks!, https://saythanks.io/to/tyagi.hardik42%40yahoo.com
Project-URL: Source, https://github.com/tyagihardik42/bingau
Keywords: binomial,gaussian,distribution
Platform: UNKNOWN
Classifier: Development Status :: 3 - Alpha
Classifier: License :: OSI Approved :: MIT License
Classifier: Programming Language :: Python :: 3
